tywrap_ir/__init__.py
tywrap_ir/__main__.py
tywrap_ir/ir.py
tywrap_ir/optimized_ir.py
tywrap_ir-0.2.0.dist-info/METADATA
tywrap_ir-0.2.0.dist-info/WHEEL
tywrap_ir-0.2.0.dist-info/entry_points.txt
tywrap_ir-0.2.0.dist-info/top_level.txt
tywrap_ir-0.2.0.dist-info/RECORD
