Metadata-Version: 2.4
Name: tywrap-ir
Version: 0.2.0
Summary: Python IR extractor for tywrap: emits versioned JSON IR for Python modules
Author: tywrap contributors
Maintainer: tywrap contributors
License: MIT
Project-URL: Homepage, https://github.com/bbopen/tywrap
Project-URL: Repository, https://github.com/bbopen/tywrap
Project-URL: Documentation, https://github.com/bbopen/tywrap#readme
Project-URL: Issues, https://github.com/bbopen/tywrap/issues
Keywords: tywrap,typescript,python,bridge,code-generation,ast,ir
Classifier: Development Status :: 3 - Alpha
Classifier: Intended Audience :: Developers
Classifier: License :: OSI Approved :: MIT License
Classifier: Operating System :: OS Independent
Classifier: Programming Language :: Python :: 3
Classifier: Programming Language :: Python :: 3.10
Classifier: Programming Language :: Python :: 3.11
Classifier: Programming Language :: Python :: 3.12
Classifier: Topic :: Software Development :: Code Generators
Classifier: Topic :: Software Development :: Libraries :: Python Modules
Classifier: Typing :: Typed
Requires-Python: >=3.10
